pychangelog2/__init__.py
pychangelog2/__main__.py
pychangelog2/_version.py
pychangelog2-1.0.2.dist-info/LICENSE
pychangelog2-1.0.2.dist-info/METADATA
pychangelog2-1.0.2.dist-info/WHEEL
pychangelog2-1.0.2.dist-info/entry_points.txt
pychangelog2-1.0.2.dist-info/top_level.txt
pychangelog2-1.0.2.dist-info/RECORD
