Metadata-Version: 2.1
Name: pychangelog2
Version: 1.0.2
Summary: rpcclient for connecting with the rpcserver
Author-email: doronz88 <doron88@gmail.com>
Maintainer-email: doronz88 <doron88@gmail.com>
License: GNU GENERAL PUBLIC LICENSE
Project-URL: Homepage, https://github.com/doronz88/pychangelog2
Project-URL: Bug Reports, https://github.com/doronz88/pychangelog2/issues
Keywords: git,changelog,version
Classifier: Development Status :: 5 - Production/Stable
Classifier: License :: OSI Approved :: GNU General Public License v3 or later (GPLv3+)
Classifier: Programming Language :: Python :: 3
Classifier: Programming Language :: Python :: 3.8
Classifier: Programming Language :: Python :: 3.9
Classifier: Programming Language :: Python :: 3.10
Classifier: Programming Language :: Python :: 3.11
Classifier: Programming Language :: Python :: 3.12
Classifier: Programming Language :: Python :: 3 :: Only
Requires-Python: >=3.8
License-File: LICENSE
Requires-Dist: click
Requires-Dist: gitpython
Provides-Extra: test
Requires-Dist: pytest ; extra == 'test'
